hypergraphx/__init__.py
hypergraphx/communities/__init__.py
hypergraphx/communities/core_periphery/__init__.py
hypergraphx/communities/core_periphery/model.py
hypergraphx/communities/hy_mmsbm/__init__.py
hypergraphx/communities/hy_mmsbm/_linear_ops.py
hypergraphx/communities/hy_mmsbm/model.py
hypergraphx/communities/hy_sc/__init__.py
hypergraphx/communities/hy_sc/model.py
hypergraphx/communities/hypergraph_mt/__init__.py
hypergraphx/communities/hypergraph_mt/model.py
hypergraphx/communities/hyperlink_comm/__init__.py
hypergraphx/communities/hyperlink_comm/hyperlink_communities.py
hypergraphx/core/__init__.py
hypergraphx/core/directed_hypergraph.py
hypergraphx/core/hypergraph.py
hypergraphx/core/multiplex_hypergraph.py
hypergraphx/core/temporal_hypergraph.py
hypergraphx/dynamics/__init__.py
hypergraphx/dynamics/contagion.py
hypergraphx/dynamics/randwalk.py
hypergraphx/dynamics/synch.py
hypergraphx/dynamics/utils.py
hypergraphx/filters/__init__.py
hypergraphx/filters/metadata_filters.py
hypergraphx/filters/statistical_filters.py
hypergraphx/generation/GAM.py
hypergraphx/generation/__init__.py
hypergraphx/generation/activity_driven.py
hypergraphx/generation/configuration_model.py
hypergraphx/generation/directed_configuration_model.py
hypergraphx/generation/hy_mmsbm_sampling.py
hypergraphx/generation/random.py
hypergraphx/generation/scale_free.py
hypergraphx/linalg/__init__.py
hypergraphx/linalg/linalg.py
hypergraphx/measures/__init__.py
hypergraphx/measures/degree.py
hypergraphx/measures/edge_similarity.py
hypergraphx/measures/eigen_centralities.py
hypergraphx/measures/s_centralities.py
hypergraphx/measures/shortest_paths.py
hypergraphx/measures/sub_hypergraph_centrality.py
hypergraphx/measures/directed/__init__.py
hypergraphx/measures/directed/degree.py
hypergraphx/measures/directed/hyperedge_signature.py
hypergraphx/measures/directed/reciprocity.py
hypergraphx/measures/multiplex/__init__.py
hypergraphx/measures/multiplex/degree.py
hypergraphx-1.7.9.dist-info/licenses/LICENSE.md
hypergraphx-1.7.9.dist-info/METADATA
hypergraphx-1.7.9.dist-info/WHEEL
hypergraphx-1.7.9.dist-info/top_level.txt
hypergraphx-1.7.9.dist-info/RECORD
